Workbook

Sheet Resumen
A1: Handoff QA Manual: Pagos, Facturas, Crédito y Deuda
A2: Generado el 2026-07-22 desde pruebas unitarias y código de servicios. Total de casos manuales: 61.
A4: Área | B4: Total | C4: P0 | D4: P1 | E4: P2 | F4: Sin iniciar | G4: Aprobado | H4: Fallido | J4: Resumen ejecución | K4: Conteo
A5: Pagos | B5: =COUNTIF('Casos Manuales'!$B$2:$B$62,A5) -> 9 | C5: =COUNTIFS('Casos Manuales'!$B$2:$B$62,A5,'Casos Manuales'!$C$2:$C$62,"P0") -> 5 | D5: =COUNTIFS('Casos Manuales'!$B$2:$B$62,A5,'Casos Manuales'!$C$2:$C$62,"P1") -> 3 | E5: =COUNTIFS('Casos Manuales'!$B$2:$B$62,A5,'Casos Manuales'!$C$2:$C$62,"P2") -> 1 | F5: =COUNTIFS('Casos Manuales'!$B$2:$B$62,A5,'Casos Manuales'!$L$2:$L$62,"Sin iniciar") -> 9 | G5: =COUNTIFS('Casos Manuales'!$B$2:$B$62,A5,'Casos Manuales'!$L$2:$L$62,"Aprobado") -> 0 | H5: =COUNTIFS('Casos Manuales'!$B$2:$B$62,A5,'Casos Manuales'!$L$2:$L$62,"Fallido") -> 0 | J5: Total general | K5: =COUNTA('Casos Manuales'!$A$2:$A$62) -> 61
A6: Balance | B6: =COUNTIF('Casos Manuales'!$B$2:$B$62,A6) -> 2 | C6: =COUNTIFS('Casos Manuales'!$B$2:$B$62,A6,'Casos Manuales'!$C$2:$C$62,"P0") -> 1 | D6: =COUNTIFS('Casos Manuales'!$B$2:$B$62,A6,'Casos Manuales'!$C$2:$C$62,"P1") -> 1 | E6: =COUNTIFS('Casos Manuales'!$B$2:$B$62,A6,'Casos Manuales'!$C$2:$C$62,"P2") -> 0 | F6: =COUNTIFS('Casos Manuales'!$B$2:$B$62,A6,'Casos Manuales'!$L$2:$L$62,"Sin iniciar") -> 2 | G6: =COUNTIFS('Casos Manuales'!$B$2:$B$62,A6,'Casos Manuales'!$L$2:$L$62,"Aprobado") -> 0 | H6: =COUNTIFS('Casos Manuales'!$B$2:$B$62,A6,'Casos Manuales'!$L$2:$L$62,"Fallido") -> 0 | J6: Conteo P0 | K6: =COUNTIF('Casos Manuales'!$C$2:$C$62,"P0") -> 31
A7: Deuda | B7: =COUNTIF('Casos Manuales'!$B$2:$B$62,A7) -> 5 | C7: =COUNTIFS('Casos Manuales'!$B$2:$B$62,A7,'Casos Manuales'!$C$2:$C$62,"P0") -> 2 | D7: =COUNTIFS('Casos Manuales'!$B$2:$B$62,A7,'Casos Manuales'!$C$2:$C$62,"P1") -> 3 | E7: =COUNTIFS('Casos Manuales'!$B$2:$B$62,A7,'Casos Manuales'!$C$2:$C$62,"P2") -> 0 | F7: =COUNTIFS('Casos Manuales'!$B$2:$B$62,A7,'Casos Manuales'!$L$2:$L$62,"Sin iniciar") -> 5 | G7: =COUNTIFS('Casos Manuales'!$B$2:$B$62,A7,'Casos Manuales'!$L$2:$L$62,"Aprobado") -> 0 | H7: =COUNTIFS('Casos Manuales'!$B$2:$B$62,A7,'Casos Manuales'!$L$2:$L$62,"Fallido") -> 0 | J7: Aprobados | K7: =COUNTIF('Casos Manuales'!$L$2:$L$62,"Aprobado") -> 0
A8: Órdenes a crédito | B8: =COUNTIF('Casos Manuales'!$B$2:$B$62,A8) -> 12 | C8: =COUNTIFS('Casos Manuales'!$B$2:$B$62,A8,'Casos Manuales'!$C$2:$C$62,"P0") -> 6 | D8: =COUNTIFS('Casos Manuales'!$B$2:$B$62,A8,'Casos Manuales'!$C$2:$C$62,"P1") -> 5 | E8: =COUNTIFS('Casos Manuales'!$B$2:$B$62,A8,'Casos Manuales'!$C$2:$C$62,"P2") -> 1 | F8: =COUNTIFS('Casos Manuales'!$B$2:$B$62,A8,'Casos Manuales'!$L$2:$L$62,"Sin iniciar") -> 12 | G8: =COUNTIFS('Casos Manuales'!$B$2:$B$62,A8,'Casos Manuales'!$L$2:$L$62,"Aprobado") -> 0 | H8: =COUNTIFS('Casos Manuales'!$B$2:$B$62,A8,'Casos Manuales'!$L$2:$L$62,"Fallido") -> 0 | J8: Fallidos | K8: =COUNTIF('Casos Manuales'!$L$2:$L$62,"Fallido") -> 0
A9: Config crédito | B9: =COUNTIF('Casos Manuales'!$B$2:$B$62,A9) -> 7 | C9: =COUNTIFS('Casos Manuales'!$B$2:$B$62,A9,'Casos Manuales'!$C$2:$C$62,"P0") -> 1 | D9: =COUNTIFS('Casos Manuales'!$B$2:$B$62,A9,'Casos Manuales'!$C$2:$C$62,"P1") -> 5 | E9: =COUNTIFS('Casos Manuales'!$B$2:$B$62,A9,'Casos Manuales'!$C$2:$C$62,"P2") -> 1 | F9: =COUNTIFS('Casos Manuales'!$B$2:$B$62,A9,'Casos Manuales'!$L$2:$L$62,"Sin iniciar") -> 7 | G9: =COUNTIFS('Casos Manuales'!$B$2:$B$62,A9,'Casos Manuales'!$L$2:$L$62,"Aprobado") -> 0 | H9: =COUNTIFS('Casos Manuales'!$B$2:$B$62,A9,'Casos Manuales'!$L$2:$L$62,"Fallido") -> 0 | J9: Bloqueados | K9: =COUNTIF('Casos Manuales'!$L$2:$L$62,"Bloqueado") -> 0
A10: Facturas | B10: =COUNTIF('Casos Manuales'!$B$2:$B$62,A10) -> 12 | C10: =COUNTIFS('Casos Manuales'!$B$2:$B$62,A10,'Casos Manuales'!$C$2:$C$62,"P0") -> 7 | D10: =COUNTIFS('Casos Manuales'!$B$2:$B$62,A10,'Casos Manuales'!$C$2:$C$62,"P1") -> 4 | E10: =COUNTIFS('Casos Manuales'!$B$2:$B$62,A10,'Casos Manuales'!$C$2:$C$62,"P2") -> 1 | F10: =COUNTIFS('Casos Manuales'!$B$2:$B$62,A10,'Casos Manuales'!$L$2:$L$62,"Sin iniciar") -> 12 | G10: =COUNTIFS('Casos Manuales'!$B$2:$B$62,A10,'Casos Manuales'!$L$2:$L$62,"Aprobado") -> 0 | H10: =COUNTIFS('Casos Manuales'!$B$2:$B$62,A10,'Casos Manuales'!$L$2:$L$62,"Fallido") -> 0
A11: Cancelaciones | B11: =COUNTIF('Casos Manuales'!$B$2:$B$62,A11) -> 8 | C11: =COUNTIFS('Casos Manuales'!$B$2:$B$62,A11,'Casos Manuales'!$C$2:$C$62,"P0") -> 7 | D11: =COUNTIFS('Casos Manuales'!$B$2:$B$62,A11,'Casos Manuales'!$C$2:$C$62,"P1") -> 0 | E11: =COUNTIFS('Casos Manuales'!$B$2:$B$62,A11,'Casos Manuales'!$C$2:$C$62,"P2") -> 1 | F11: =COUNTIFS('Casos Manuales'!$B$2:$B$62,A11,'Casos Manuales'!$L$2:$L$62,"Sin iniciar") -> 8 | G11: =COUNTIFS('Casos Manuales'!$B$2:$B$62,A11,'Casos Manuales'!$L$2:$L$62,"Aprobado") -> 0 | H11: =COUNTIFS('Casos Manuales'!$B$2:$B$62,A11,'Casos Manuales'!$L$2:$L$62,"Fallido") -> 0
A12: Reportes | B12: =COUNTIF('Casos Manuales'!$B$2:$B$62,A12) -> 6 | C12: =COUNTIFS('Casos Manuales'!$B$2:$B$62,A12,'Casos Manuales'!$C$2:$C$62,"P0") -> 2 | D12: =COUNTIFS('Casos Manuales'!$B$2:$B$62,A12,'Casos Manuales'!$C$2:$C$62,"P1") -> 2 | E12: =COUNTIFS('Casos Manuales'!$B$2:$B$62,A12,'Casos Manuales'!$C$2:$C$62,"P2") -> 2 | F12: =COUNTIFS('Casos Manuales'!$B$2:$B$62,A12,'Casos Manuales'!$L$2:$L$62,"Sin iniciar") -> 6 | G12: =COUNTIFS('Casos Manuales'!$B$2:$B$62,A12,'Casos Manuales'!$L$2:$L$62,"Aprobado") -> 0 | H12: =COUNTIFS('Casos Manuales'!$B$2:$B$62,A12,'Casos Manuales'!$L$2:$L$62,"Fallido") -> 0
A15: Guía QA
A16: 1 | B16: Ejecutar primero casos P0. Cubren movimientos de dinero, creación de factura, registro/liquidación de crédito y reversas de cancelación.
A17: 2 | B17: Usar tenant/base QA desechable. Los casos mutan saldos, deudas, facturas, pagos y estados de órdenes.
A18: 3 | B18: Registrar IDs de objetos y valores financieros antes/después en la hoja Casos Manuales.
A19: 4 | B19: Importar este XLSX en Google Sheets si se necesita una hoja compartida nativa.
A20: 5 | B20: Crear una Google Sheet nativa requiere el plugin Google Drive, que no está instalado en esta sesión de Codex.
A21: 6 | B21: Mapa de Fuentes contiene referencias de código y pruebas para auditoría.

Sheet Casos Manuales
A1: ID Caso | B1: Área | C1: Prioridad | D1: Escenario | E1: Precondiciones / Datos | F1: Pasos manuales | G1: Resultados esperados | H1: Post-checks / Evidencia | I1: Pruebas fuente | J1: Código fuente | K1: Notas QA | L1: Estado | M1: Responsable | N1: Fecha probada | O1: Resultado real | P1: Liga defecto | Q1: Notas de ejecución
A2: PAY-001 | B2: Pagos | C2: P0 | D2: Orden de contado pagada totalmente en efectivo | E2: El cliente tiene una orden de contado pendiente con total_amount = 100.00 y sin pagos existentes. | F2: 1. Abrir la pantalla de pago de la orden. 2. Usar monto 100.00 y método de pago Efectivo/cash. 3. Enviar el pago. 4. Abrir la orden y el historial de pagos del cliente. | G2: - La respuesta o la UI indica éxito. - Existe un Payment completado por 100.00 con método cash. - La orden queda pagada según total_paid y no se genera movimiento de saldo ni deuda. | H2: Revisar Payment admin/lista, total_paid de la orden e historial de pagos del cliente. | I2: payment/tests.py:76, payment/tests.py:118 | J2: payment/services.py:285, payment/services.py:68, orders/views.py:113 | L2: Sin iniciar
A3: PAY-002 | B3: Pagos | C3: P0 | D3: Pago dividido usa saldo del cliente más otro método | E3: Saldo del cliente = 30.00. Orden de contado con total_amount = 50.00. | F3: 1. Abrir la pantalla de checkout/crear orden. 2. Confirmar que el desglose muestra 30.00 de saldo y 20.00 restante. 3. Elegir efectivo o transferencia para el monto restante. 4. Completar el pago. | G3: - Se crean dos pagos: balance 30.00 y el método seleccionado 20.00. - El saldo del cliente baja a 0.00. - Existe BalanceTransaction con transaction_type payment por 30.00. - La orden queda en estado COMPLETED. | H3: El historial del cliente debe mostrar la deducción de saldo y el pago externo. | I3: payment/tests.py:56, orders/tests.py:1443 | J3: payment/services.py:216, payment/services.py:68, orders/static/orders/js/create_order.js:1075 | L3: Sin iniciar
A4: PAY-003 | B4: Pagos | C4: P0 | D4: Se rechaza pago dividido cuando la suma no coincide con el total | E4: Orden de contado con total_amount = 100.00. | F4: 1. Enviar un payload de pago dividido o selección en UI cuyos montos sumen 90.00. 2. Intentar completar la orden. | G4: - El pago se rechaza con mensaje de que la suma de pagos debe ser igual al total de la orden. - No se crean pagos nuevos. - El estado de la orden no cambia a COMPLETED por este envío. | H4: Comparar el conteo de pagos de la orden antes y después. | I4: payment/tests.py:56, payment/tests.py:272 | J4: payment/services.py:216 | L4: Sin iniciar
A5: PAY-004 | B5: Pagos | C5: P0 | D5: Pago con saldo insuficiente es rechazado | E5: Saldo del cliente = 30.00. Total de la orden o monto de pago = 50.00. | F5: 1. Intentar pagar 50.00 usando Saldo/balance. 2. Enviar el pago. | G5: - El pago se rechaza con mensaje de saldo insuficiente. - No se crea Payment completado con método balance. - El saldo del cliente permanece en 30.00. | H5: Revisar saldo del cliente y lista de BalanceTransaction. | I5: orders/tests.py:1317, tests/test_balance_credit_integration.py:190 | J5: payment/services.py:68, payment/models.py:69, clients/services/balance_service.py:120 | L5: Sin iniciar
A6: PAY-005 | B6: Pagos | C6: P1 | D6: Cantidad cobrada mayor al total agrega excedente al saldo del cliente | E6: Orden de contado con total_amount = 100.00. Conocer el saldo inicial del cliente. | F6: 1. Completar checkout con cantidad_cobrada = 120.00. 2. Usar un método de pago válido para el total de la orden. 3. Abrir el detalle del cliente después del pago. | G6: - El pago se procesa correctamente. - La orden guarda cantidad_cobrada = 120.00. - El saldo del cliente aumenta en 20.00. - BalanceTransaction tiene transaction_type added_in_order y referencia la orden. | H6: Verificar que la respuesta muestre balance_added/new_client_balance cuando aplique. | I6: payment/tests.py:43 | J6: payment/services.py:337, clients/services/balance_service.py:59 | L6: Sin iniciar
A7: PAY-006 | B7: Pagos | C7: P0 | D7: Cantidad cobrada menor al total de la orden es rechazada | E7: Orden con total_amount = 100.00. | F7: 1. Intentar checkout con cantidad_cobrada = 99.99. 2. Enviar el pago. | G7: - El envío es rechazado. - El error indica que la cantidad cobrada no puede ser menor al total de la orden. - No se agrega saldo y no debe registrarse pago exitoso por este envío. | H7: Comparar pagos y saldo antes/después. | I7: payment/tests.py:35 | J7: payment/services.py:33, payment/services.py:337 | L7: Sin iniciar
A8: PAY-007 | B8: Pagos | C8: P1 | D8: Método de pago inválido en liquidación es rechazado | E8: Existe una orden y el usuario inició sesión. | F8: 1. Enviar una solicitud de pago con un método fuera del conjunto permitido. 2. Observar la respuesta. | G8: - El pago se rechaza con 'Método de pago inválido para este flujo'. - No se persiste ningún Payment. | H8: Revisar el conteo de pagos de la orden. | I8: payment/tests.py:153 | J8: payment/services.py:12, payment/services.py:68 | L8: Sin iniciar
A9: PAY-008 | B9: Pagos | C9: P2 | D9: Las notas de checkout se guardan en la orden | E9: Existe una orden pendiente. | F9: 1. Capturar una nota durante checkout/pago. 2. Completar o enviar la solicitud de pago. 3. Reabrir la orden. | G9: - Las notas de la orden se guardan sin espacios sobrantes. - Las notas en blanco se guardan como vacío/null. | H9: Revisar el campo en detalle o admin de la orden. | I9: orders/tests.py:333, orders/tests.py:347 | J9: payment/services.py:33, orders/views.py:463 | L9: Sin iniciar
A10: PAY-009 | B10: Pagos | C10: P1 | D10: El marcador pending_credit completado no cuenta como dinero pagado | E10: La orden a crédito solo tiene un Payment pending_credit cambiado a completado y no tiene pago cash/balance. | F10: 1. Abrir la orden o los totales de factura/pago. 2. Comparar total_paid contra total_amount. | G10: - El total_paid de la orden es 0.00 para el marcador pending_credit. - La orden sigue apareciendo como no pagada hasta que exista un pago completado distinto de pending_credit. | H10: Revisar filtros de órdenes no pagadas y total_payments de factura. | I10: payment/tests.py:284 | J10: invoice/models.py:47, invoice/models.py:136, payment/models.py:49 | L10: Sin iniciar
A11: BAL-001 | B11: Balance | C11: P0 | D11: Depósito manual de saldo actualiza saldo y auditoría | E11: Existe un cliente activo. Usuario QA con sesión iniciada. | F11: 1. Abrir Agregar/Gestionar saldo del cliente. 2. Seleccionar tipo de transacción Depósito. 3. Capturar monto 200.00 y notas detalladas de al menos 10 caracteres. 4. Enviar y abrir el historial de pagos del cliente. | G11: - El saldo del cliente aumenta en 200.00. - Se crea BalanceTransaction con saldos antes/después, created_by y notas. - El mensaje de éxito muestra el saldo actualizado. | H11: Verificar en admin/historial de BalanceTransaction. | I11: tests/test_balance_credit_history.py:1 | J11: clients/views.py:942, clients/forms.py:12, clients/services/balance_service.py:59 | L11: Sin iniciar
A12: BAL-002 | B12: Balance | C12: P1 | D12: Depósito manual exige monto positivo y notas significativas | E12: Existe un cliente activo. | F12: 1. Abrir Agregar saldo. 2. Intentar monto 0.00 o notas menores a 10 caracteres. 3. Enviar. | G12: - La validación del formulario bloquea el envío. - No se crea BalanceTransaction. - El saldo del cliente no cambia. | H12: Confirmar mensajes de validación y ausencia de nueva transacción. | I12: tests/test_balance_credit_history.py:1 | J12: clients/forms.py:12, clients/services/balance_service.py:59 | L12: Sin iniciar
A13: DEBT-001 | B13: Deuda | C13: P0 | D13: Pago manual de deuda reduce current_debt | E13: Cliente con current_debt = 300.00 y credit_limit configurado. | F13: 1. Abrir Gestionar crédito/pay-credit del cliente. 2. Seleccionar Pago de deuda. 3. Capturar monto 100.00, descripción y notas detalladas. 4. Enviar y abrir el detalle del cliente. | G13: - El current_debt del cliente baja a 200.00. - Se crea CreditTransaction transaction_type payment con debt_before 300.00 y debt_after 200.00. - El crédito disponible aumenta en 100.00. | H13: Verificar CreditTransaction y totales del reporte global de crédito. | I13: tests/test_balance_credit_history.py:1 | J13: clients/views.py:854, clients/forms.py:64, clients/services/balance_service.py:261 | L13: Sin iniciar
... A62: REP-006 | B62: Reportes | C62: P2 | D62: Modo créditos de lista de clientes filtra clientes con deuda | E62: Al menos un cliente tiene current_debt > 0 y al menos un cliente activo tiene deuda cero. | F62: 1. Abrir lista de clientes con mode=credits. 2. Usar búsqueda y paginación. | G62: - Solo aparecen clientes con current_debt mayor a 0. - Búsqueda y paginación preservan mode=credits. - Título/subtítulo indican contexto de cobranza de crédito. | H62: Usar detalle del cliente para clientes seleccionados con deuda. | I62: clients/tests.py:596, clients/tests.py:640 | J62: clients/views.py:777 | L62: Sin iniciar

Sheet Datos de Prueba
A1: ID Setup | B1: Entidad | C1: Instrucciones de preparación | D1: Usado por | E1: Notas
A2: SET-001 | B2: Usuario | C2: Crear o usar una cuenta QA staff/superuser. | D2: Todos los casos admin y reportes | E2: Usar la misma cuenta para que created_by sea fácil de auditar.
A3: SET-002 | B3: Producto | C3: Crear producto QA Garrafón con precio conocido, por ejemplo 25.00. | D3: Casos de creación de órdenes | E3: Cualquier producto sirve si los totales de orden coinciden con los montos del escenario.
A4: SET-003 | B4: Cliente contado | C4: Crear QA Contado con balance 0.00, credit_limit 0.00, current_debt 0.00. | D4: PAY-001, PAY-003, PAY-006 | E4: Usar para flujos ordinarios de pago.
A5: SET-004 | B5: Cliente con saldo | C5: Crear QA Balance con balance 100.00 y current_debt 0.00. | D5: PAY-002, PAY-004, BAL-001, BAL-002, CAN-003 | E5: Registrar saldo inicial antes de cada prueba.
A6: SET-005 | B6: Cliente crédito OK | C6: Crear QA Crédito OK con balance 0.00, credit_limit 500.00, current_debt 0.00, can_pay_with_credit true, monthly_cutoff last_day. | D6: CRED-001, CRED-006, CRED-008, REP-001 | E6: Usar montos exactos de deuda/límite según cada escenario.
A7: SET-006 | B7: Cliente crédito mixto | C7: Crear QA Crédito Mixto con balance 30.00, credit_limit 100.00, current_debt 0.00, can_pay_with_credit true. | D7: CRED-002, CRED-005 | E7: Reiniciar saldo/deuda entre ejecuciones.
A8: SET-007 | B8: Cliente crédito bloqueado | C8: Crear QA Crédito Bloqueado con balance 30.00, credit_limit 200.00, current_debt 0.00, can_pay_with_credit false. | D8: CRED-004, CFG-001 | E8: La etiqueta del checkbox está invertida: marcado significa bloquear crédito.
A9: SET-008 | B9: Corporativo listo para factura | C9: Crear QA Factura Corp con type corporate, InvoiceData RFC/razon_social y una dirección fiscal/facturación activa. | D9: INV-001 a INV-012 | E9: Las pruebas usan RFC placeholder tipo AAA010101AAA.
A10: SET-009 | B10: Par sucursal/corporativo | C10: Crear clientes corporativo y sucursal para herencia y validación de factura; variar completitud fiscal corporativa. | D10: CFG-003, CFG-004, CFG-005, INV-010 | E10: Los datos fiscales de sucursal no deben saltarse la validación fiscal corporativa.
A11: SET-010 | B11: Dataset reporte crédito | C11: Crear clientes estilo Tempano/Vigor con compras a crédito fechadas 2026-04-01 y 2026-07-01. | D11: REP-001, REP-002, REP-003, REP-004 | E11: Usar base QA desechable porque las fechas son específicas del escenario.
A12: SET-011 | B12: Términos invoice_due | C12: Para pruebas invoice_due, configurar requires_billing true y max_payment_days 30. | D12: CFG-002, CFG-007, REP-003 | E12: Órdenes sin factura no deben tener fecha de vencimiento.
A13: SET-012 | B13: Limpieza/reinicio | C13: Después de cada caso con movimiento de dinero, registrar saldos/deudas iniciales y finales, IDs de orden, pago y transacciones. | D13: Todos los casos financieros | E13: Esta hoja es para notas de ejecución manual, no para teardown automatizado.

Sheet Escenario-Codigo
A1: Área | B1: Comportamiento | C1: Código fuente principal | D1: Pruebas automatizadas | E1: IDs de casos manuales
A2: Pagos | B2: Enrutamiento de solicitud de pago, pago único/múltiple, cantidad_cobrada | C2: payment/services.py:33, payment/services.py:216, payment/services.py:285, payment/services.py:337 | D2: payment/tests.py:26, payment/tests.py:56, payment/tests.py:76, payment/tests.py:118 | E2: PAY-001 a PAY-009
A3: Pagos | B3: Pantalla de pago de orden, métodos válidos, entrada para liquidar crédito pendiente | C3: orders/views.py:67, orders/views.py:113 | D3: payment/tests.py:294, orders/tests.py:1511 | E3: PAY-001, CRED-008, CRED-009
A4: Balance | B4: Mutaciones de saldo y filas de auditoría | C4: clients/services/balance_service.py:59, clients/services/balance_service.py:120, clients/models.py:320 | D4: tests/test_balance_credit_history.py:1, orders/tests.py:554 | E4: BAL-001, BAL-002, CAN-003
A5: Deuda | B5: Pago de deuda, pago desde saldo, cambios de límite de crédito | C5: clients/services/balance_service.py:261, clients/services/balance_service.py:431, clients/services/balance_service.py:488 | D5: tests/test_balance_credit_history.py:1 | E5: DEBT-001 a DEBT-005
A6: Órdenes a crédito | B6: Ciclo de vida para registrar y liquidar órdenes a crédito | C6: payment/services.py:403, payment/services.py:423, payment/services.py:501, payment/services.py:108 | D6: payment/tests.py:205, payment/tests.py:316, payment/tests.py:344, payment/tests.py:396 | E6: CRED-001 a CRED-011
A7: Config crédito | B7: Disponibilidad de crédito, paro de emergencia, override/herencia de sucursal | C7: clients/models.py:195, clients/models.py:199, clients/services/client_service.py:51, clients/views.py:262 | D7: clients/tests_credit_management.py:75, clients/tests_credit_management.py:170, clients/tests_credit_management.py:301 | E7: CFG-001 a CFG-005
A8: Términos crédito | B8: Cálculo de corte mensual y fecha de vencimiento por factura | C8: clients/services/pending_payment_service.py:27, clients/services/pending_payment_service.py:40 | D8: clients/tests_credit_terms.py:13, clients/tests_credit_terms.py:33, clients/tests_credit_terms.py:46 | E8: CFG-006, CFG-007, REP-003
A9: Facturas | B9: Órdenes facturables, validación de tope, creación y sincronización de factura | C9: invoice/services.py:265, invoice/services.py:314, invoice/services.py:352, invoice/services.py:476, invoice/services.py:534 | D9: invoice/tests.py:38, invoice/tests.py:130, invoice/tests.py:413, invoice/tests.py:469 | E9: INV-001 a INV-012
A10: Facturas | B10: Vistas admin de factura y acción masiva Crear factura | C10: invoice/views.py:120, invoice/views.py:142, orders/views.py:253 | D10: invoice/tests.py:523, invoice/tests.py:542, orders/tests.py:1043 | E10: INV-006, INV-012
A11: Cancelaciones | B11: Reversas financieras y lógica review_required | C11: orders/services.py:237, orders/services.py:267, orders/services.py:281, orders/services.py:302, orders/services.py:329 | D11: orders/tests.py:656, orders/tests.py:693, orders/tests.py:721, orders/tests.py:757, orders/tests.py:819, orders/tests.py:844 | E11: CAN-001 a CAN-008
A12: Reportes | B12: Reportes de crédito global y por cliente | C12: clients/services/credit_report_service.py:250, clients/services/credit_report_service.py:261, report/views.py:235, report/views.py:262 | D12: clients/tests_credit_report_service.py:73, clients/tests_credit_report_service.py:120, report/tests.py:506, report/tests.py:520 | E12: REP-001 a REP-006
A13: Detalle cliente | B13: Estado de crédito del cliente, vencidos, facturas e historial de pagos | C13: clients/views.py:576, clients/views.py:608, clients/services/pending_payment_service.py:94 | D13: clients/tests.py:416, clients/tests.py:501, clients/tests_credit_management.py:542 | E13: CRED-006, REP-002, REP-006

Sheet Guía de Ejecución
A1: sla | B1: Guía
A2: Propósito | B2: Handoff QA manual para escenarios de pagos, facturas, crédito y deuda trazados desde las pruebas unitarias y el código fuente actual.
A3: Entregable principal | B3: Importar este XLSX en Google Sheets. Crear una hoja nativa requeriría instalar el plugin Google Drive.
A4: Orden recomendado | B4: Ejecutar setup y luego casos P0 primero: PAY, CRED, INV, CAN, REP. Completar P1/P2 después de validar flujos financieros base.
A5: Ambiente de ejecución | B5: Usar base de datos o tenant QA desechable. Muchos casos mutan saldos, deudas, pagos, facturas y estado de cancelación.
A6: Registro de evidencia | B6: Para cada caso, llenar Estado, Responsable, Fecha probada, Resultado real, Liga defecto y Notas en Casos Manuales.
A7: Enfoque de auditoría | B7: Registrar siempre ID de cliente, orden, pago, factura, BalanceTransaction y CreditTransaction cuando existan.
A8: Trazabilidad | B8: Usar la pestaña Mapa de Fuentes para mapear cada caso manual contra pruebas automatizadas y código de servicio.
A9: Terminología | B9: Saldo = balance prepago. Deuda/current_debt = monto adeudado. Payment pending_credit = marcador de crédito, no dinero pagado.
